hibernation_no1/__init__.py
hibernation_no1/version.py
hibernation_no1/cloud/__init__.py
hibernation_no1/cloud/google/__init__.py
hibernation_no1/cloud/google/dvc.py
hibernation_no1/cloud/google/storage.py
hibernation_no1/configs/__init__.py
hibernation_no1/configs/config.py
hibernation_no1/configs/utils.py
hibernation_no1/database/__init__.py
hibernation_no1/database/mysql.py
hibernation_no1/mmdet/__init__.py
hibernation_no1/mmdet/checkpoint.py
hibernation_no1/mmdet/eval.py
hibernation_no1/mmdet/inference.py
hibernation_no1/mmdet/optimizer.py
hibernation_no1/mmdet/registry.py
hibernation_no1/mmdet/runner.py
hibernation_no1/mmdet/scatter.py
hibernation_no1/mmdet/utils.py
hibernation_no1/mmdet/visualization.py
hibernation_no1/mmdet/data/__init__.py
hibernation_no1/mmdet/data/datacontainer.py
hibernation_no1/mmdet/data/dataloader.py
hibernation_no1/mmdet/data/dataset.py
hibernation_no1/mmdet/data/sampler.py
hibernation_no1/mmdet/data/api/__init__.py
hibernation_no1/mmdet/data/api/coco.py
hibernation_no1/mmdet/data/transforms/__init__.py
hibernation_no1/mmdet/data/transforms/collect.py
hibernation_no1/mmdet/data/transforms/compose.py
hibernation_no1/mmdet/data/transforms/defaultformatbundle.py
hibernation_no1/mmdet/data/transforms/loadannotations.py
hibernation_no1/mmdet/data/transforms/loadimagefronfile.py
hibernation_no1/mmdet/data/transforms/multiscaleflipaug.py
hibernation_no1/mmdet/data/transforms/normalize.py
hibernation_no1/mmdet/data/transforms/pad.py
hibernation_no1/mmdet/data/transforms/randomflip.py
hibernation_no1/mmdet/data/transforms/resize.py
hibernation_no1/mmdet/data/transforms/utils.py
hibernation_no1/mmdet/hooks/__init__.py
hibernation_no1/mmdet/hooks/checkpoint.py
hibernation_no1/mmdet/hooks/custom.py
hibernation_no1/mmdet/hooks/hook.py
hibernation_no1/mmdet/hooks/itertime.py
hibernation_no1/mmdet/hooks/logger.py
hibernation_no1/mmdet/hooks/optimizer.py
hibernation_no1/mmdet/hooks/stepupdater.py
hibernation_no1/mmdet/modules/__init__.py
hibernation_no1-0.2.31.dist-info/METADATA
hibernation_no1-0.2.31.dist-info/WHEEL
hibernation_no1-0.2.31.dist-info/top_level.txt
hibernation_no1-0.2.31.dist-info/RECORD
