Metadata-Version: 2.1
Name: hibernation-no1
Version: 0.2.31
Summary: package for only hibernation_no1
Home-page: https://github.com/HibernationNo1/hibernation_no1-package.git
Author: taeuk4958
Author-email: taeuk4958@gmail.com
License: Apache License 2.0
Requires-Dist: addict
Requires-Dist: dvc[gs]
Requires-Dist: numpy
